aio_retrying.py
aio_retrying-1.0.3.dist-info/LICENSE
aio_retrying-1.0.3.dist-info/METADATA
aio_retrying-1.0.3.dist-info/WHEEL
aio_retrying-1.0.3.dist-info/RECORD
