Metadata-Version: 2.1
Name: aio-retrying
Version: 1.0.3
Summary: new version async retrying package.
License: MIT
Author: Daoji
Author-email: daoji.chang@gmail.com
Requires-Python: >=3.8,<4.0
Classifier: License :: OSI Approved :: MIT License
Classifier: Programming Language :: Python :: 3
Classifier: Programming Language :: Python :: 3.8
Classifier: Programming Language :: Python :: 3.9
Classifier: Programming Language :: Python :: 3.10
Classifier: Programming Language :: Python :: 3.11
Classifier: Programming Language :: Python :: 3.12
Requires-Dist: async-timeout (>=4.0.3,<5.0.0)
